[
    {
        "id": 3,
        "Question": "In what year was the company that was founded as Sound of Music added to the S&P 500?",
        "answer": "1999"
    },
    {
        "id": 4,
        "Question": "Who was the first African American mayor of the most populous city in the United States?",
        "answer": "David Dinkins"
    },
    {
        "id": 5,
        "Question": "When did the last king from Britain's House of Hanover die?",
        "answer": "20 June 1837"
    },
    {
        "id": 6,
        "Question": "When did the president who set the precedent of a two term limit enter office?",
        "answer": "April 30, 1789"
    },
    {
        "id": 7,
        "Question": "When did the president who set the precedent of a two term limit leave office?",
        "answer": "March 4, 1797"
    },
    {
        "id": 8,
        "Question": "How many people died in the second most powerful earthquake ever recorded?",
        "answer": "131"
    },
    {
        "id": 9,
        "Question": "Can people who have celiac eat camel meat?",
        "answer": "Yes"
    },
    {
        "id": 10,
        "Question": "What was the final book written by the author of On the Origin of Species?",
        "answer": "The Formation of Vegetable Mould Through the Action of Worms"
    },
    {
        "id": 11,
        "Question": "When was the company that built the first steam locomotive to carry passengers on a public rail line founded?",
        "answer": "1823"
    },
    {
        "id": 12,
        "Question": "Which Theranos whistleblower is not related to a senior American government official?",
        "answer": "Erika Cheung"
    },
    {
        "id": 13,
        "Question": "What is the fastest air-breathing manned aircraft mostly made out of?",
        "answer": "Titanium"
    },
    {
        "id": 14,
        "Question": "Who built the fastest air-breathing manned aircraft?",
        "answer": "Lockheed Corporation"
    },
    {
        "id": 15,
        "Question": "When was the author of The Population Bomb born?",
        "answer": "May 29, 1932"
    },
    {
        "id": 16,
        "Question": "When did the author of Annabel Lee enlist in the army?",
        "answer": "1827"
    },
    {
        "id": 17,
        "Question": "What was the religion of the inventor of the Polio vaccine?",
        "answer": "Jewish"
    },
    {
        "id": 18,
        "Question": "Who was the second wife of the founder of CNN?",
        "answer": "Jane Shirley Smith"
    },
    {
        "id": 19,
        "Question": "When did the first prime minister of the Russian Empire come into office?",
        "answer": "November 6, 1905"
    },
    {
        "id": 20,
        "Question": "What is the primary male hormone derived from?",
        "answer": "cholesterol"
    },
    {
        "id": 21,
        "Question": "The Filipino statesman who established the government-in-exile during the outbreak of World War II was also the mayor of what city?",
        "answer": "Quezon City"
    },
    {
        "id": 22,
        "Question": "Where was the person who shared the Nobel Prize in Physics in 1954 with Max Born born?",
        "answer": "Oranienburg, Germany"
    },
    {
        "id": 23,
        "Question": "When was the person who shared the Nobel Prize in Physics in 1954 with Max Born born?",
        "answer": "January 8, 1891"
    },
    {
        "id": 24,
        "Question": "What was the founding date of the university in which Plotonium was discovered?",
        "answer": "March 23, 1868"
    },
    {
        "id": 25,
        "Question": "The material out of which the Great Sphinx of Giza is made of is mainly composed of what mineral?",
        "answer": "calcite"
    },
    {
        "id": 26,
        "Question": "The husband of Lady Godiva was Earl of which Anglic kingdom?",
        "answer": "Mercia"
    },
    {
        "id": 27,
        "Question": "The machine used to extract honey from honeycombs uses which physical force?",
        "answer": "Centrifugal Force"
    },
    {
        "id": 28,
        "Question": "What is the third letter of the top level domain of the military?",
        "answer": "l"
    },
    {
        "id": 29,
        "Question": "In what year was the government department where the internet originated at founded?",
        "answer": "1947"
    },
    {
        "id": 30,
        "Question": "The main actor of Indiana Jones is a licensed what?",
        "answer": "pilot"
    },
    {
        "id": 31,
        "Question": "When was the person after which the Hubble Space Telescope is named after born?",
        "answer": "November 20, 1889"
    },
    {
        "id": 32,
        "Question": "When did the person who gave the Checkers speech die?",
        "answer": "April 22, 1994"
    },
    {
        "id": 33,
        "Question": "When was the philosopher that formulated the hard problem of consciousness born?",
        "answer": "April 20, 1966"
    },
    {
        "id": 34,
        "Question": "What is the capital of the second largest state in the US by area?",
        "answer": "Austin"
    },
    {
        "id": 35,
        "Question": "What is the maximum airspeed (in km/h) of the third fastest bird?",
        "answer": "320 km/h"
    },
    {
        "id": 36,
        "Question": "Who founded the city where the founder of geometry lived?",
        "answer": "Alexander the Great"
    },
    {
        "id": 37,
        "Question": "What is the capital of the country where yoga originated?",
        "answer": "New Delhi"
    },
    {
        "id": 38,
        "Question": "The fourth largest city in Germany was originally called what?",
        "answer": "Colonia Claudia Ara Agrippinensium"
    },
    {
        "id": 39,
        "Question": "When did Nirvana's second most selling studio album come out?",
        "answer": "September 13, 1993"
    },
    {
        "id": 40,
        "Question": "What was the job of the father of the founder of psychoanalysis?",
        "answer": "wool merchant"
    }
]